math_function/Basicmath.py
math_function/__init__.py
math_function/numbers.py
math_function-0.0.1.dist-info/LICENSE.txt
math_function-0.0.1.dist-info/METADATA
math_function-0.0.1.dist-info/WHEEL
math_function-0.0.1.dist-info/top_level.txt
math_function-0.0.1.dist-info/RECORD
